django_group/__init__.py
django_group/admin.py
django_group/apps.py
django_group/models.py
django_group/signals.py
django_group/tests.py
django_group/urls.py
django_group/views.py
django_group/migrations/0001_initial.py
django_group/migrations/__init__.py
sample_project/__init__.py
sample_project/asgi.py
sample_project/settings.py
sample_project/urls.py
sample_project/wsgi.py
Django_Group_Extend-0.1.3.dist-info/LICENSE
Django_Group_Extend-0.1.3.dist-info/METADATA
Django_Group_Extend-0.1.3.dist-info/WHEEL
Django_Group_Extend-0.1.3.dist-info/top_level.txt
Django_Group_Extend-0.1.3.dist-info/RECORD
